[{"id":"e6fd4eab-cee5-4379-bf5f-eb9b3bbfe0a0","title":"Di","status":"INCOMPLETE","createdAt":"2022-04-06T14:32:35.422Z","updatedAt":"2022-04-06T14:40:25.663Z"},{"id":"a153555f-cc14-4160-b8f9-bb5d0a56ef8b","title":"Lunch","status":"PENDING","createdAt":"2022-04-06T14:34:46.690Z","updatedAt":"2022-04-07T06:00:46.162Z"},{"id":"8dbafaab-54f9-4440-85b5-97e285d9dc56","title":"Lunch","status":"COMPLETE","createdAt":"2022-04-06T14:35:52.948Z"},{"id":"556a16c6-ed56-4704-a91d-4b71267c3124","title":"Lunch","status":"COMPLETE","createdAt":"2022-04-06T14:37:33.589Z"},{"id":"24e6ef8a-6e5c-4e86-9fb0-55b550c21559","title":"Lunch","status":"INCOMPLETE","createdAt":"2022-04-06T14:38:24.298Z"},{"id":"46468a6c-4fff-49d2-9bbb-70a0320533dc","title":"Lunch","status":"COMPLETE","createdAt":"2022-04-06T14:38:32.681Z"},{"id":"957dbde1-9aca-46c7-ac66-03def95d3e66","title":"Wow","status":"PENDING","createdAt":"2022-04-07T06:01:23.687Z"}]